nexstar_control/__init__.py
nexstar_control/device.py
nexstar_control-1.0.2.dist-info/METADATA
nexstar_control-1.0.2.dist-info/WHEEL
nexstar_control-1.0.2.dist-info/licenses/LICENSE
nexstar_control-1.0.2.dist-info/RECORD
