Metadata-Version: 2.4
Name: nexstar-control
Version: 1.0.2
Summary: A library that can be used to communicate and control Celestron NexStar telescope devices.
License-Expression: MIT
License-File: LICENSE
Author: Tristen Georgiou
Author-email: tristen.georgiou@gmail.com
Requires-Python: >=3.11
Classifier: Programming Language :: Python :: 3
Classifier: Programming Language :: Python :: 3.11
Classifier: Programming Language :: Python :: 3.12
Classifier: Programming Language :: Python :: 3.13
Classifier: Programming Language :: Python :: 3.14
Requires-Dist: pyserial (>=3.5,<4.0)
Requires-Dist: tzdata
Project-URL: Changelog, https://github.com/tristeng/nexstar-control/blob/main/CHANGELOG.md
Project-URL: Homepage, https://github.com/tristeng/nexstar-control
Project-URL: Issues, https://github.com/tristeng/nexstar-control/issues
Project-URL: Repository, https://github.com/tristeng/nexstar-control.git
